{
  "candidate": {
    "source_id": "hkex",
    "source_name": "HKEXnews",
    "source_domain": "www1.hkexnews.hk",
    "market": "HK",
    "company_id": "03968",
    "ticker": "03968",
    "company_name": "CM BANK",
    "report_type": "annual",
    "report_family": "annual",
    "form": "annual",
    "title": "Annual Report 2025",
    "accession_number": "12124325",
    "primary_document": "2026042700894.pdf",
    "report_end": "2025-12-31",
    "published_at": "2026-04-27",
    "accepted_at": null,
    "document_url": "https://www1.hkexnews.hk/listedco/listconews/sehk/2026/0427/2026042700894.pdf",
    "landing_url": "https://www1.hkexnews.hk/listedco/listconews/sehk/2026/0427/2026042700894.pdf",
    "file_format": "pdf",
    "language": "en",
    "inline_xbrl": null,
    "metadata": {
      "news_id": "12124325",
      "stock_name": "CM BANK",
      "short_text": "Financial Statements/ESG Information - [Annual Report]",
      "long_text": "Financial Statements/ESG Information - [Annual Report]",
      "file_info": "30MB"
    }
  },
  "downloaded_file": {
    "file_name": "CM-BANK_HK_03968_2025-12-31_年报_2026-04-27_hkex_d61941c9.pdf",
    "saved_path": "/home/maoyd/siq-research-engine/data/market-report-finder/downloads/HK/CM-BANK/2025/年报/CM-BANK_HK_03968_2025-12-31_年报_2026-04-27_hkex_d61941c9.pdf",
    "size_bytes": 31036663,
    "content_type": "application/pdf",
    "content_sha256": "63484250ac0f53f5a0bcd0fdbbe05d531f6a53e81d8e2f3e11b0517f6fb8e32a"
  }
}
